CropwiseWorker/__init__.py
CropwiseWorker/cropwiseworker.py
CropwiseWorker-0.1.1.dist-info/METADATA
CropwiseWorker-0.1.1.dist-info/WHEEL
CropwiseWorker-0.1.1.dist-info/top_level.txt
CropwiseWorker-0.1.1.dist-info/RECORD
