Metadata-Version: 2.1
Name: CropwiseWorker
Version: 0.1.1
Summary: Модуль реализует функции для работы с API цифровой платформы управления агропредприятием Cropwise Operations.
Author: Molev Arkhip
Author-email: jobarkhip@gmail.com
Classifier: Development Status :: 3 - Alpha
Classifier: Intended Audience :: Developers
Classifier: License :: OSI Approved :: Apache Software License
Classifier: Natural Language :: Russian
Classifier: Programming Language :: Python :: 3
Requires-Python: >=3.6
Requires-Dist: requests
Requires-Dist: pandas
